[{"id":"5ad9f367459a0c8b7ac1bc9a7e9faa28","sport_key":"basketball_wncaab","sport_title":"WNCAAB","commence_time":"2026-03-05T22:02:44Z","home_team":"Syracuse Orange","away_team":"California Golden Bears","bookmakers":[{"key":"betmgm","title":"BetMGM","last_update":"2026-03-06T00:08:38Z","markets":[{"key":"h2h","last_update":"2026-03-06T00:08:38Z","outcomes":[{"name":"California Golden Bears","price":1600},{"name":"Syracuse Orange","price":-10000}]}]}]},{"id":"5e91bc93c82a2058b212e0dae14c9fed","sport_key":"basketball_wncaab","sport_title":"WNCAAB","commence_time":"2026-03-05T22:31:00Z","home_team":"Saint Mary's Gaels","away_team":"San Diego Toreros","bookmakers":[{"key":"betrivers","title":"BetRivers","last_update":"2026-03-06T00:08:53Z","markets":[{"key":"h2h","last_update":"2026-03-06T00:08:53Z","outcomes":[{"name":"Saint Mary's Gaels","price":-120},{"name":"San Diego Toreros","price":-120}]}]},{"key":"betmgm","title":"BetMGM","last_update":"2026-03-06T00:08:38Z","markets":[{"key":"h2h","last_update":"2026-03-06T00:08:38Z","outcomes":[{"name":"Saint Mary's Gaels","price":-130},{"name":"San Diego Toreros","price":100}]}]}]},{"id":"73f3ca021bc6c77a21fb03a208828aa8","sport_key":"basketball_wncaab","sport_title":"WNCAAB","commence_time":"2026-03-05T22:45:00Z","home_team":"Furman Paladins","away_team":"Mercer Bears","bookmakers":[{"key":"betrivers","title":"BetRivers","last_update":"2026-03-06T00:08:53Z","markets":[{"key":"h2h","last_update":"2026-03-06T00:08:53Z","outcomes":[{"name":"Furman Paladins","price":-137},{"name":"Mercer Bears","price":-104}]}]},{"key":"betmgm","title":"BetMGM","last_update":"2026-03-06T00:08:38Z","markets":[{"key":"h2h","last_update":"2026-03-06T00:08:38Z","outcomes":[{"name":"Furman Paladins","price":-125},{"name":"Mercer Bears","price":-102}]}]}]},{"id":"a26c410ac6357c57d9214e43d14532c6","sport_key":"basketball_wncaab","sport_title":"WNCAAB","commence_time":"2026-03-05T23:00:00Z","home_team":"Ole Miss Rebels","away_team":"Auburn Tigers","bookmakers":[{"key":"betmgm","title":"BetMGM","last_update":"2026-03-06T00:08:38Z","markets":[{"key":"h2h","last_update":"2026-03-06T00:08:38Z","outcomes":[{"name":"Auburn Tigers","price":1600},{"name":"Ole Miss Rebels","price":-10000}]}]}]},{"id":"20db892c156344cbdc6f1bd2399543ff","sport_key":"basketball_wncaab","sport_title":"WNCAAB","commence_time":"2026-03-05T23:02:00Z","home_team":"Radford Highlanders","away_team":"Charleston Southern Buccaneers","bookmakers":[{"key":"betmgm","title":"BetMGM","last_update":"2026-03-06T00:08:38Z","markets":[{"key":"h2h","last_update":"2026-03-06T00:08:38Z","outcomes":[{"name":"Charleston Southern Buccaneers","price":1600},{"name":"Radford Highlanders","price":-10000}]}]}]},{"id":"fc82a41f0140ebfb1de3efc3165a43cf","sport_key":"basketball_wncaab","sport_title":"WNCAAB","commence_time":"2026-03-05T23:02:00Z","home_team":"Maine Black Bears","away_team":"New Hampshire Wildcats","bookmakers":[{"key":"betmgm","title":"BetMGM","last_update":"2026-03-06T00:08:38Z","markets":[{"key":"h2h","last_update":"2026-03-06T00:08:38Z","outcomes":[{"name":"Maine Black Bears","price":-10000},{"name":"New Hampshire Wildcats","price":1600}]}]}]},{"id":"2ae20714f31438983a07a7d48ae85850","sport_key":"basketball_wncaab","sport_title":"WNCAAB","commence_time":"2026-03-05T23:04:00Z","home_team":"Vermont Catamounts","away_team":"Albany Great Danes","bookmakers":[{"key":"betrivers","title":"BetRivers","last_update":"2026-03-06T00:08:53Z","markets":[{"key":"h2h","last_update":"2026-03-06T00:08:53Z","outcomes":[{"name":"Albany Great Danes","price":700},{"name":"Vermont Catamounts","price":-2000}]}]},{"key":"betmgm","title":"BetMGM","last_update":"2026-03-06T00:08:38Z","markets":[{"key":"h2h","last_update":"2026-03-06T00:08:38Z","outcomes":[{"name":"Albany Great Danes","price":600},{"name":"Vermont Catamounts","price":-1100}]}]}]},{"id":"e127d2341379732825c3cccd1c9ea3e0","sport_key":"basketball_wncaab","sport_title":"WNCAAB","commence_time":"2026-03-05T23:08:00Z","home_team":"Binghamton Bearcats","away_team":"Bryant Bulldogs","bookmakers":[{"key":"betrivers","title":"BetRivers","last_update":"2026-03-06T00:08:53Z","markets":[{"key":"h2h","last_update":"2026-03-06T00:08:53Z","outcomes":[{"name":"Binghamton Bearcats","price":-245},{"name":"Bryant Bulldogs","price":165}]}]},{"key":"betmgm","title":"BetMGM","last_update":"2026-03-06T00:08:38Z","markets":[{"key":"h2h","last_update":"2026-03-06T00:08:38Z","outcomes":[{"name":"Binghamton Bearcats","price":-175},{"name":"Bryant Bulldogs","price":135}]}]}]},{"id":"081acb3578e31d286215f5018af39a31","sport_key":"basketball_wncaab","sport_title":"WNCAAB","commence_time":"2026-03-05T23:30:00Z","home_team":"UMBC Retrievers","away_team":"NJIT Highlanders","bookmakers":[{"key":"betrivers","title":"BetRivers","last_update":"2026-03-06T00:08:54Z","markets":[{"key":"h2h","last_update":"2026-03-06T00:08:53Z","outcomes":[{"name":"NJIT Highlanders","price":-530},{"name":"UMBC Retrievers","price":300}]}]},{"key":"betmgm","title":"BetMGM","last_update":"2026-03-06T00:08:38Z","markets":[{"key":"h2h","last_update":"2026-03-06T00:08:38Z","outcomes":[{"name":"NJIT Highlanders","price":-325},{"name":"UMBC Retrievers","price":240}]}]}]},{"id":"376010de5c76b8b0e3bcb9490008ebd6","sport_key":"basketball_wncaab","sport_title":"WNCAAB","commence_time":"2026-03-05T23:32:00Z","home_team":"Iowa State Cyclones","away_team":"Arizona St Sun Devils","bookmakers":[{"key":"betrivers","title":"BetRivers","last_update":"2026-03-06T00:08:54Z","markets":[{"key":"h2h","last_update":"2026-03-06T00:08:53Z","outcomes":[{"name":"Arizona St Sun Devils","price":-125},{"name":"Iowa State Cyclones","price":-114}]}]},{"key":"fanduel","title":"FanDuel","last_update":"2026-03-06T00:08:46Z","markets":[{"key":"h2h","last_update":"2026-03-06T00:08:46Z","outcomes":[{"name":"Arizona St Sun Devils","price":-144},{"name":"Iowa State Cyclones","price":108}]}]},{"key":"draftkings","title":"DraftKings","last_update":"2026-03-06T00:08:38Z","markets":[{"key":"h2h","last_update":"2026-03-06T00:08:38Z","outcomes":[{"name":"Arizona St Sun Devils","price":-135},{"name":"Iowa State Cyclones","price":105}]}]},{"key":"betmgm","title":"BetMGM","last_update":"2026-03-06T00:08:38Z","markets":[{"key":"h2h","last_update":"2026-03-06T00:08:38Z","outcomes":[{"name":"Arizona St Sun Devils","price":-145},{"name":"Iowa State Cyclones","price":110}]}]}]},{"id":"6a904c8777eb76808e492fbfb3f14562","sport_key":"basketball_wncaab","sport_title":"WNCAAB","commence_time":"2026-03-05T23:33:45Z","home_team":"Michigan St Spartans","away_team":"Illinois Fighting Illini","bookmakers":[{"key":"draftkings","title":"DraftKings","last_update":"2026-03-06T00:08:38Z","markets":[{"key":"h2h","last_update":"2026-03-06T00:08:38Z","outcomes":[{"name":"Illinois Fighting Illini","price":-120},{"name":"Michigan St Spartans","price":-110}]}]},{"key":"betmgm","title":"BetMGM","last_update":"2026-03-06T00:08:38Z","markets":[{"key":"h2h","last_update":"2026-03-06T00:08:38Z","outcomes":[{"name":"Illinois Fighting Illini","price":-120},{"name":"Michigan St Spartans","price":-105}]}]},{"key":"betrivers","title":"BetRivers","last_update":"2026-03-06T00:08:54Z","markets":[{"key":"h2h","last_update":"2026-03-06T00:08:53Z","outcomes":[{"name":"Illinois Fighting Illini","price":-177},{"name":"Michigan St Spartans","price":120}]}]},{"key":"fanduel","title":"FanDuel","last_update":"2026-03-06T00:07:59Z","markets":[{"key":"h2h","last_update":"2026-03-06T00:07:59Z","outcomes":[{"name":"Illinois Fighting Illini","price":-108},{"name":"Michigan St Spartans","price":-122}]}]}]},{"id":"ae15cf5da83f77093e6f85d7efa8c211","sport_key":"basketball_wncaab","sport_title":"WNCAAB","commence_time":"2026-03-06T00:30:00Z","home_team":"Central Arkansas Bears","away_team":"North Alabama Lions","bookmakers":[{"key":"betrivers","title":"BetRivers","last_update":"2026-03-06T00:08:54Z","markets":[{"key":"h2h","last_update":"2026-03-06T00:08:53Z","outcomes":[{"name":"Central Arkansas Bears","price":-530},{"name":"North Alabama Lions","price":330}]}]},{"key":"betmgm","title":"BetMGM","last_update":"2026-03-06T00:08:38Z","markets":[{"key":"h2h","last_update":"2026-03-06T00:08:38Z","outcomes":[{"name":"Central Arkansas Bears","price":-450},{"name":"North Alabama Lions","price":350}]}]}]},{"id":"1a58b507234a7551f513202bc5692466","sport_key":"basketball_wncaab","sport_title":"WNCAAB","commence_time":"2026-03-06T00:30:00Z","home_team":"Virginia Tech Hokies","away_team":"Georgia Tech Yellow Jackets","bookmakers":[{"key":"betrivers","title":"BetRivers","last_update":"2026-03-06T00:08:54Z","markets":[{"key":"h2h","last_update":"2026-03-06T00:08:53Z","outcomes":[{"name":"Georgia Tech Yellow Jackets","price":215},{"name":"Virginia Tech Hokies","price":-305}]}]},{"key":"draftkings","title":"DraftKings","last_update":"2026-03-06T00:08:38Z","markets":[{"key":"h2h","last_update":"2026-03-06T00:08:38Z","outcomes":[{"name":"Georgia Tech Yellow Jackets","price":230},{"name":"Virginia Tech Hokies","price":-285}]}]},{"key":"betmgm","title":"BetMGM","last_update":"2026-03-06T00:08:38Z","markets":[{"key":"h2h","last_update":"2026-03-06T00:08:38Z","outcomes":[{"name":"Georgia Tech Yellow Jackets","price":260},{"name":"Virginia Tech Hokies","price":-325}]}]},{"key":"fanduel","title":"FanDuel","last_update":"2026-03-06T00:08:46Z","markets":[{"key":"h2h","last_update":"2026-03-06T00:08:46Z","outcomes":[{"name":"Georgia Tech Yellow Jackets","price":280},{"name":"Virginia Tech Hokies","price":-420}]}]}]},{"id":"3b03d68fa2642d0d500bffdba47fa4f2","sport_key":"basketball_wncaab","sport_title":"WNCAAB","commence_time":"2026-03-06T00:30:00Z","home_team":"La Salle Explorers","away_team":"Saint Louis Billikens","bookmakers":[{"key":"betrivers","title":"BetRivers","last_update":"2026-03-06T00:08:54Z","markets":[{"key":"h2h","last_update":"2026-03-06T00:08:53Z","outcomes":[{"name":"La Salle Explorers","price":-180},{"name":"Saint Louis Billikens","price":133}]}]},{"key":"betmgm","title":"BetMGM","last_update":"2026-03-06T00:08:38Z","markets":[{"key":"h2h","last_update":"2026-03-06T00:08:38Z","outcomes":[{"name":"La Salle Explorers","price":-175},{"name":"Saint Louis Billikens","price":145}]}]}]},{"id":"d47ec9c19bdb131188d0ee08f18af162","sport_key":"basketball_wncaab","sport_title":"WNCAAB","commence_time":"2026-03-06T01:30:00Z","home_team":"Tennessee Volunteers","away_team":"Alabama Crimson Tide","bookmakers":[{"key":"betrivers","title":"BetRivers","last_update":"2026-03-06T00:08:54Z","markets":[{"key":"h2h","last_update":"2026-03-06T00:08:53Z","outcomes":[{"name":"Alabama Crimson Tide","price":150},{"name":"Tennessee Volunteers","price":-205}]}]},{"key":"draftkings","title":"DraftKings","last_update":"2026-03-06T00:08:38Z","markets":[{"key":"h2h","last_update":"2026-03-06T00:08:38Z","outcomes":[{"name":"Alabama Crimson Tide","price":164},{"name":"Tennessee Volunteers","price":-198}]}]},{"key":"fanduel","title":"FanDuel","last_update":"2026-03-06T00:08:46Z","markets":[{"key":"h2h","last_update":"2026-03-06T00:08:46Z","outcomes":[{"name":"Alabama Crimson Tide","price":132},{"name":"Tennessee Volunteers","price":-178}]}]}]},{"id":"77346b9de0d0ad1a766ba8f3b2eb1786","sport_key":"basketball_wncaab","sport_title":"WNCAAB","commence_time":"2026-03-06T01:30:00Z","home_team":"Longwood Lancers","away_team":"UNC Asheville Bulldogs","bookmakers":[{"key":"betrivers","title":"BetRivers","last_update":"2026-03-06T00:08:54Z","markets":[{"key":"h2h","last_update":"2026-03-06T00:08:53Z","outcomes":[{"name":"Longwood Lancers","price":-1000},{"name":"UNC Asheville Bulldogs","price":540}]}]},{"key":"betmgm","title":"BetMGM","last_update":"2026-03-06T00:07:02Z","markets":[{"key":"h2h","last_update":"2026-03-06T00:07:02Z","outcomes":[{"name":"Longwood Lancers","price":-650},{"name":"UNC Asheville Bulldogs","price":475}]}]}]},{"id":"8dfb368b199ecedf70b8e4c177295658","sport_key":"basketball_wncaab","sport_title":"WNCAAB","commence_time":"2026-03-06T02:00:00Z","home_team":"Colorado Buffaloes","away_team":"Kansas Jayhawks","bookmakers":[{"key":"betrivers","title":"BetRivers","last_update":"2026-03-06T00:08:54Z","markets":[{"key":"h2h","last_update":"2026-03-06T00:08:53Z","outcomes":[{"name":"Colorado Buffaloes","price":-122},{"name":"Kansas Jayhawks","price":-109}]}]},{"key":"draftkings","title":"DraftKings","last_update":"2026-03-06T00:08:38Z","markets":[{"key":"h2h","last_update":"2026-03-06T00:08:38Z","outcomes":[{"name":"Colorado Buffaloes","price":-122},{"name":"Kansas Jayhawks","price":102}]}]},{"key":"fanduel","title":"FanDuel","last_update":"2026-03-06T00:08:46Z","markets":[{"key":"h2h","last_update":"2026-03-06T00:08:46Z","outcomes":[{"name":"Colorado Buffaloes","price":-125},{"name":"Kansas Jayhawks","price":-106}]}]}]},{"id":"f2baaccd568e1d808767c24b630d0d57","sport_key":"basketball_wncaab","sport_title":"WNCAAB","commence_time":"2026-03-06T02:00:00Z","home_team":"UC Davis Aggies","away_team":"Long Beach St 49ers","bookmakers":[]},{"id":"f5b6f5a3fde05028253ff661737e974d","sport_key":"basketball_wncaab","sport_title":"WNCAAB","commence_time":"2026-03-06T02:00:00Z","home_team":"Maryland Terrapins","away_team":"Oregon Ducks","bookmakers":[{"key":"betrivers","title":"BetRivers","last_update":"2026-03-06T00:08:54Z","markets":[{"key":"h2h","last_update":"2026-03-06T00:08:53Z","outcomes":[{"name":"Maryland Terrapins","price":-335},{"name":"Oregon Ducks","price":230}]}]},{"key":"draftkings","title":"DraftKings","last_update":"2026-03-06T00:08:38Z","markets":[{"key":"h2h","last_update":"2026-03-06T00:08:38Z","outcomes":[{"name":"Maryland Terrapins","price":-278},{"name":"Oregon Ducks","price":225}]}]},{"key":"fanduel","title":"FanDuel","last_update":"2026-03-06T00:08:46Z","markets":[{"key":"h2h","last_update":"2026-03-06T00:08:46Z","outcomes":[{"name":"Maryland Terrapins","price":-280},{"name":"Oregon Ducks","price":200}]}]}]}]
